{
  "generated_at": "2026-03-01T14:24:42+01:00",
  "phase": {
    "current": 1,
    "name": "Baseline (200q)",
    "gates_passed": true
  },
  "pipelines": {
    "standard": {
      "accuracy": 94.0,
      "tested": 50,
      "correct": 47,
      "errors": 1,
      "target": 85.0,
      "met": true,
      "gap": 9.0
    },
    "graph": {
      "accuracy": 80.0,
      "tested": 50,
      "correct": 40,
      "errors": 0,
      "target": 70.0,
      "met": true,
      "gap": 10.0
    },
    "quantitative": {
      "accuracy": 92.0,
      "tested": 50,
      "correct": 46,
      "errors": 1,
      "target": 85.0,
      "met": true,
      "gap": 7.0
    },
    "orchestrator": {
      "accuracy": 80.0,
      "tested": 50,
      "correct": 40,
      "errors": 2,
      "target": 70.0,
      "met": true,
      "gap": 10.0
    }
  },
  "overall": {
    "accuracy": 86.5,
    "target": 75.0,
    "met": true
  },
  "blockers": [],
  "next_action": "Phase 1 COMPLETE \u2014 run Phase 2: python3 eval/run-eval-parallel.py --dataset phase-2 --reset",
  "last_iteration": {
    "id": "iter-2026-03-01T14-24-19",
    "label": "autorun-s66",
    "timestamp": "2026-03-01T14:24:25+01:00",
    "total_tested": 0,
    "overall_accuracy_pct": 0,
    "pipelines": {}
  },
  "totals": {
    "unique_questions": 2816,
    "test_runs": 10649,
    "iterations": 1403
  }
}